orders/__init__.py
orders/apps/__init__.py
orders/apps/orders/__init__.py
orders/apps/orders/all_orders_form.py
orders/apps/orders/all_orders_list.py
orders/apps/orders/orderexpensecode_list.py
orders/apps/orders/orderfile_list.py
orders/apps/orders/orders_form.py
orders/apps/orders/orders_list.py
orders/apps/orders/orders_view.py
orders/migrations/__init__.py
orders/models/__init__.py
orders/models/order.py
orders/models/order_expensecode.py
orders/models/order_file.py
orders/models/order_queryset.py
core_orders-0.3.dist-info/METADATA
core_orders-0.3.dist-info/WHEEL
core_orders-0.3.dist-info/top_level.txt
core_orders-0.3.dist-info/RECORD
