Metadata-Version: 2.1
Name: core-orders
Version: 0.3
Summary: Research CORE ERM - orders module
Home-page: https://github.com/research-core/core-orders
Author: Ricardo Ribeiro, Hugo Cachitas
Author-email: ricardojvr@gmail.com, hugo.cachitas@research.fchampalimaud.org
License: MIT
Platform: UNKNOWN
